{
    "description": "A gender modality that is neither cisgender nor transgender. Not to be confused with ipsogender.",
    "name": "isogender",
    "aliases": [
        "isogender"
    ],
    "umbrella term": [
        null
    ],
    "census percentage": 0.0,
    "related identities": [
        null
    ],
    "flag": [
        "https://static.miraheze.org/nonbinarywiki/1/17/Isogender_flag.png"
    ],
    "alternative flags": [
        "https://static.miraheze.org/nonbinarywiki/d/d1/Isogender_alt_flag.png"
    ],
    "wiki link": null
}