{
    "description": "One of many ''nounself pronouns'''. Created by Tumblr user trashqan in 2014. A robot themed set.",
    "aliases": [
        "ai",
        "ain",
        "aire",
        "aires"
    ],
    "number": null,
    "subject": [
        "ai"
    ],
    "object": [
        "ain"
    ],
    "possessive adjective": [
        "aire"
    ],
    "possessive": [
        "aires"
    ],
    "reflexive": [
        "aiself",
        "ainself"
    ],
    "census percentage": 0.0,
    "wiki link": {}
}